{
  "name": "oasis-abyss-dark",
  "cursor_bg": "#1C1C1C",
  "cursor_fg": "#D6CE7C",
  "header_bg": "#E26E6E",
  "header_fg": "#000000",
  "fixed_column_bg": "#1C1C1C",
  "col_odd_fg": "#F0EBE6",
  "col_even_fg": "#FFDACC",
  "row_odd_bg": "#141414",
  "row_even_bg": "#000000",
  "scrollbar_bg": "#000000",
  "scrollbar_fg": "#D6CE7C",
  "search_match_bg": "#532E2E",
  "search_match_fg": "#7FCF78",
  "mark_bg": "#532E2E",
  "highlight": "#FF7979",
  "accent": "#7FCF78",
  "status_tailing": "#8FD1C7",
  "status_loading": "#FFA0A0",
  "muted": "#7A7662",
  "border": "#D6CE7C",
  "brand": "#D6CE7C"
}