{
  "bg_core": "#f7e2d4",
  "bg_mantle": "#f5d9c7",
  "bg_shadow": "#f2d1ba",
  "bg_surface": "#f0c8ad",
  "fg_core": "#524943",
  "fg_strong": "#66432b",
  "fg_muted": "#5f6971",
  "fg_dim": "#89827d",
  "theme_primary": "#910303",
  "theme_secondary": "#944f0a",
  "theme_accent": "#366860",
  "error": "#750e0e",
  "warning": "#5c540b",
  "info": "#0d506c",
  "hint": "#0b5e52",
  "ok": "#1c5d0b",
  "black": "#4b4b4b",
  "red": "#ae1212",
  "green": "#2b6144",
  "yellow": "#5e581f",
  "blue": "#13589c",
  "magenta": "#7323d2",
  "cyan": "#315e59",
  "white": "#4e4b43",
  "bright_black": "#514a44",
  "bright_red": "#ae1212",
  "bright_green": "#316223",
  "bright_yellow": "#804913",
  "bright_blue": "#215d75",
  "bright_magenta": "#7223d3",
  "bright_cyan": "#305f58",
  "bright_white": "#6e400b",
  "color0": "#4b4b4b",
  "color1": "#ae1212",
  "color2": "#2b6144",
  "color3": "#5e581f",
  "color4": "#13589c",
  "color5": "#7323d2",
  "color6": "#315e59",
  "color7": "#4e4b43",
  "color8": "#514a44",
  "color9": "#ae1212",
  "color10": "#316223",
  "color11": "#804913",
  "color12": "#215d75",
  "color13": "#7223d3",
  "color14": "#305f58",
  "color15": "#6e400b"
}